testtool.py
testtool-0.0.2.dist-info/LICENSE.txt
testtool-0.0.2.dist-info/METADATA
testtool-0.0.2.dist-info/WHEEL
testtool-0.0.2.dist-info/top_level.txt
testtool-0.0.2.dist-info/RECORD
